flowhunt/__init__.py
flowhunt/api_client.py
flowhunt/api_response.py
flowhunt/configuration.py
flowhunt/exceptions.py
flowhunt/py.typed
flowhunt/rest.py
flowhunt/api/__init__.py
flowhunt/api/agent_grids_api.py
flowhunt/api/airtable_api.py
flowhunt/api/api_keys_api.py
flowhunt/api/atlassian_api.py
flowhunt/api/chatbots_api.py
flowhunt/api/credits_api.py
flowhunt/api/documents_api.py
flowhunt/api/fine_tunings_api.py
flowhunt/api/flow_assistant_v3_api.py
flowhunt/api/flow_messages_api.py
flowhunt/api/flow_sessions_api.py
flowhunt/api/flow_webhooks_api.py
flowhunt/api/flows_api.py
flowhunt/api/git_hub_api.py
flowhunt/api/google_ads_api.py
flowhunt/api/google_api.py
flowhunt/api/hub_spot_api.py
flowhunt/api/images_api.py
flowhunt/api/instagram_api.py
flowhunt/api/integrations_api.py
flowhunt/api/logs_api.py
flowhunt/api/mcp_servers_api.py
flowhunt/api/media_api.py
flowhunt/api/memory_api.py
flowhunt/api/microsoft_outlook_api.py
flowhunt/api/observability_driver_api.py
flowhunt/api/photo_ai_api.py
flowhunt/api/prompts_api.py
flowhunt/api/schedules_api.py
flowhunt/api/semantic_search_api.py
flowhunt/api/serp_api.py
flowhunt/api/shopify_api.py
flowhunt/api/slack_api.py
flowhunt/api/tags_api.py
flowhunt/api/tracking_api.py
flowhunt/api/v3_api.py
flowhunt/api/wix_api.py
flowhunt/api/word_press_api.py
flowhunt/api/workspaces_api.py
flowhunt/models/__init__.py
flowhunt/models/agent_grid_bulk_insert_response.py
flowhunt/models/agent_grid_create_request.py
flowhunt/models/agent_grid_field_request.py
flowhunt/models/agent_grid_field_response.py
flowhunt/models/agent_grid_field_type.py
flowhunt/models/agent_grid_import_error.py
flowhunt/models/agent_grid_import_start_response.py
flowhunt/models/agent_grid_import_status_response.py
flowhunt/models/agent_grid_preview_response.py
flowhunt/models/agent_grid_response.py
flowhunt/models/agent_grid_row_insert_request.py
flowhunt/models/agent_grid_row_insert_response.py
flowhunt/models/agent_grid_rows_bulk_insert_request.py
flowhunt-3.17.2.dist-info/licenses/LICENSE.txt
flowhunt-3.17.2.dist-info/METADATA
flowhunt-3.17.2.dist-info/WHEEL
flowhunt-3.17.2.dist-info/top_level.txt
flowhunt-3.17.2.dist-info/RECORD
