Metadata-Version: 2.4
Name: flowhunt
Version: 3.17.2
Summary: FlowHunt
Home-page: https://github.com/QualityUnit/flowhunt-python-sdk
Author: OpenAPI Generator community
Author-email: FlowHunt <support@flowhunt.io>
License-Expression: GPL-2.0
Project-URL: Homepage, https://flowhunt.io
Project-URL: Repository, https://github.com/QualityUnit/flowhunt-python-sdk
Project-URL: Documentation, https://github.com/QualityUnit/flowhunt-python-sdk/blob/main/README.md
Project-URL: Bug Tracker, https://github.com/QualityUnit/flowhunt-python-sdk/issues
Keywords: OpenAPI,OpenAPI-Generator,FlowHunt
Requires-Python: >=3.9
License-File: LICENSE.txt
Requires-Dist: urllib3<3.0.0,>=2.1.0
Requires-Dist: python-dateutil>=2.8.2
Requires-Dist: pydantic>=2
Requires-Dist: typing-extensions>=4.7.1
Dynamic: author
Dynamic: home-page
Dynamic: license-file
